laracna/__init__.py
laracna/http_cache.py
laracna/scraper.py
laracna-0.0.1.dist-info/LICENSE
laracna-0.0.1.dist-info/METADATA
laracna-0.0.1.dist-info/WHEEL
laracna-0.0.1.dist-info/top_level.txt
laracna-0.0.1.dist-info/RECORD
