Metadata-Version: 2.1
Name: laracna
Version: 0.0.1
Summary: Custom Spider tool
Home-page: https://github.com/Beirdo/laracna
License: UNKNOWN
Platform: UNKNOWN
License-File: LICENSE
Requires-Dist: requests
